big_g-1.0.3.dist-info/DESCRIPTION.rst
big_g-1.0.3.dist-info/METADATA
big_g-1.0.3.dist-info/RECORD
big_g-1.0.3.dist-info/WHEEL
big_g-1.0.3.dist-info/entry_points.txt
big_g-1.0.3.dist-info/metadata.json
big_g-1.0.3.dist-info/top_level.txt
object_tracking/__init__.py
object_tracking/object_tracking.py
